bh_vim/__init__.py
bh_vim/__main__.py
bh_vim/cmds/vim/__init__.py
bh_vim-0.0.0b0.dist-info/METADATA
bh_vim-0.0.0b0.dist-info/WHEEL
bh_vim-0.0.0b0.dist-info/entry_points.txt
bh_vim-0.0.0b0.dist-info/top_level.txt
bh_vim-0.0.0b0.dist-info/RECORD
